[
  {
    "id": 1,
    "topic": "algebra",
    "level": "AMC",
    "problem": "If $x + y = 10$ and $xy = 20$, what is $x^2 + y^2$?",
    "answer": 60,
    "note": "Use identity: (x+y)^2 = x^2 + 2xy + y^2 => x^2+y^2 = 100 - 40 = 60"
  },
  {
    "id": 2,
    "topic": "combinatorics",
    "level": "AMC",
    "problem": "How many ways can 5 people be seated in a row if two specific people must NOT sit next to each other?",
    "answer": 72,
    "note": "Total 5! - (arrangements where they ARE adjacent: 4! * 2) = 120 - 48 = 72"
  },
  {
    "id": 3,
    "topic": "number_theory",
    "level": "AMC",
    "problem": "Find the sum of all positive integers $n$ less than 100 such that $n$ is divisible by 3 but not by 9.",
    "answer": 1116,
    "note": "Multiples of 3 below 100: 3+6+...+99 = 1683. Multiples of 9 below 100: 9+18+...+99 = 567. Ans = 1683 - 567 = 1116"
  },
  {
    "id": 4,
    "topic": "geometry",
    "level": "AMC",
    "problem": "In a right triangle, the two legs have lengths 5 and 12. What is the area of the square drawn on the hypotenuse?",
    "answer": 169,
    "note": "Hypotenuse^2 = 5^2 + 12^2 = 25 + 144 = 169. Area of square on hypotenuse = 169."
  },
  {
    "id": 5,
    "topic": "algebra",
    "level": "AIME",
    "problem": "Let $a$, $b$, $c$ be positive real numbers satisfying $a + b + c = 1$. Find the minimum integer value of $\\frac{1}{a+b} + \\frac{1}{b+c} + \\frac{1}{a+c}$.",
    "answer": 5,
    "note": "By AM-HM inequality, sum >= 9/2 = 4.5, so the minimum integer value >= 4.5 is 5. The infimum 4.5 is never achieved."
  },
  {
    "id": 6,
    "topic": "number_theory",
    "level": "AIME",
    "problem": "Find the number of integers from 1 to 1000 (inclusive) that are divisible by at least one of 3, 5, or 7.",
    "answer": 543,
    "note": "Inclusion-exclusion: |A|+|B|+|C| - |AB| - |AC| - |BC| + |ABC| = 333+200+142 - 66 - 47 - 28 + 9 = 543"
  },
  {
    "id": 7,
    "topic": "combinatorics",
    "level": "AIME",
    "problem": "A committee of 5 people is to be chosen from a group of 6 men and 4 women. How many committees include at least 2 women?",
    "answer": 186,
    "note": "Total = C(10,5) = 252. Subtract 0-women: C(6,5)=6. Subtract 1-woman: C(4,1)*C(6,4)=60. So >= 2 women = 252 - 6 - 60 = 186."
  }
]
